ytsum/__init__.py
ytsum/distill.py
ytsum/main.py
ytsum-0.1.9.dist-info/METADATA
ytsum-0.1.9.dist-info/WHEEL
ytsum-0.1.9.dist-info/top_level.txt
ytsum-0.1.9.dist-info/RECORD
