Metadata-Version: 2.1
Name: ytsum
Version: 0.1.9
Summary: Summarize YouTube video instantly with the power of distill-whisper and Mixtral-8B
Home-page: https://github.com/Siris2314/ytsum
Author: Arihant Tripathi
Author-email: tarihant2001@gmail.com
Classifier: Programming Language :: Python :: 3
Classifier: License :: OSI Approved :: MIT License
Classifier: Operating System :: OS Independent
Requires-Python: >=3.7
Requires-Dist: torch ==2.1.1+cu118
Requires-Dist: requests ==2.32.3
Requires-Dist: pytube ==15.0.0
Requires-Dist: transformers ==4.36.2
Requires-Dist: langchain ==0.2.3
Requires-Dist: langchain-community ==0.2.4
Requires-Dist: langchain-together ==0.1.3
Requires-Dist: pytubefix ==8.10.2
